README
setup.cfg
setup.py
mission/__init__.py
mission/mission.py
mission.egg-info/PKG-INFO
mission.egg-info/SOURCES.txt
mission.egg-info/dependency_links.txt
mission.egg-info/top_level.txt