Metadata-Version: 1.0
Name: mission
Version: 0.0.1
Summary: Simple threadpool
Home-page: https://github.com/yogapan/mission
Author: YogaPan
Author-email: godhand1234567@gmail.com
License: UNKNOWN
Platform: UNKNOWN
